ctc/__init__.py
ctc-2.0.1.dist-info/LICENSE
ctc-2.0.1.dist-info/METADATA
ctc-2.0.1.dist-info/WHEEL
ctc-2.0.1.dist-info/top_level.txt
ctc-2.0.1.dist-info/RECORD
