Metadata-Version: 2.1
Name: ctc
Version: 2.0.1
Summary: windows console text color (reupload 2 version)
Home-page: UNKNOWN
Author: Minecraft_XiaoYu
Author-email: UNKNOWN
License: MIT
Platform: UNKNOWN
